tessif_calliope_0_6_6post1/__init__.py
tessif_calliope_0_6_6post1/optimize.py
tessif_calliope_0_6_6post1/post_process.py
tessif_calliope_0_6_6post1/transform.py
tessif_calliope_0_6_6post1-0.1.2.dist-info/LICENSE
tessif_calliope_0_6_6post1-0.1.2.dist-info/WHEEL
tessif_calliope_0_6_6post1-0.1.2.dist-info/METADATA
tessif_calliope_0_6_6post1-0.1.2.dist-info/RECORD
