Metadata-Version: 2.1
Name: tessif-calliope-0-6-6post1
Version: 0.1.2
Summary: Tessif-Plugin for providing Calliope version 0.6.6post1 support.
Home-page: https://github.com/tZ3ma/tessif_calliope_0_6_6post1
License: MIT
Keywords: Tessif,Tessif-Calliope,ESSMOS,optimization,energy supply system modelling
Author: Mathias Ammon
Author-email: tz3ma.coding@use.startmail.com
Requires-Python: >=3.8,<3.9
Classifier: License :: OSI Approved :: MIT License
Classifier: Programming Language :: Python :: 3
Classifier: Programming Language :: Python :: 3.8
Requires-Dist: calliope (==0.6.6post1)
Requires-Dist: numpy (<1.20)
Requires-Dist: tessif (>=0.0.25)
Project-URL: Repository, https://github.com/tZ3ma/tessif_calliope_0_6_6post1
